{
  "ModelType": "Query",
  "Code": "avr_ClaimsSelectRows_d2",
  "Name": "avr_ClaimsSelectRows_d2",
  "ConnectionCode": "Default",
  "IsUsedForRightsFilter": false,
  "IsAnonymousAccess": false,
  "Parameters": [
    {
      "Code": "@OrgID",
      "Name": "OrgID",
      "ParameterType": "Integer",
      "RightsFilterQueryCode": "GlodalFilter_UserOrganizations"
    },
    {
      "Code": "@pageOffsetRows",
      "Name": "pageOffsetRows",
      "ParameterType": "Integer",
      "IsPageOffsetRows": true
    },
    {
      "Code": "@TypeId",
      "Name": "TypeId",
      "ParameterType": "Integer",
      "RightsFilterQueryCode": "GlobalFilter_ClaimTypes"
    },
    {
      "Code": "@pageLimitRows",
      "Name": "pageLimitRows",
      "ParameterType": "Integer",
      "IsPageLimitRows": true
    }
  ]
}